tmam/__helpers.py
tmam/__init__.py
tmam/evals/__init__.py
tmam/evals/all.py
tmam/evals/bias_detection.py
tmam/evals/hallucination.py
tmam/evals/toxicity.py
tmam/evals/utils.py
tmam/instrumentation/ag2/__init__.py
tmam/instrumentation/ag2/ag2.py
tmam/instrumentation/ai21/__init__.py
tmam/instrumentation/ai21/ai21.py
tmam/instrumentation/ai21/async_ai21.py
tmam/instrumentation/ai21/utils.py
tmam/instrumentation/anthropic/__init__.py
tmam/instrumentation/anthropic/anthropic.py
tmam/instrumentation/anthropic/async_anthropic.py
tmam/instrumentation/anthropic/utils.py
tmam/instrumentation/assemblyai/__init__.py
tmam/instrumentation/assemblyai/assemblyai.py
tmam/instrumentation/astra/__init__.py
tmam/instrumentation/astra/astra.py
tmam/instrumentation/astra/async_astra.py
tmam/instrumentation/astra/utils.py
tmam/instrumentation/azure_ai_inference/__init__.py
tmam/instrumentation/azure_ai_inference/async_azure_ai_inference.py
tmam/instrumentation/azure_ai_inference/azure_ai_inference.py
tmam/instrumentation/azure_ai_inference/utils.py
tmam/instrumentation/bedrock/__init__.py
tmam/instrumentation/bedrock/bedrock.py
tmam/instrumentation/bedrock/utils.py
tmam/instrumentation/chroma/__init__.py
tmam/instrumentation/chroma/chroma.py
tmam/instrumentation/cohere/__init__.py
tmam/instrumentation/cohere/async_cohere.py
tmam/instrumentation/cohere/cohere.py
tmam/instrumentation/controlflow/__init__.py
tmam/instrumentation/controlflow/controlflow.py
tmam/instrumentation/crawl4ai/__init__.py
tmam/instrumentation/crawl4ai/async_crawl4ai.py
tmam/instrumentation/crawl4ai/crawl4ai.py
tmam/instrumentation/crewai/__init__.py
tmam/instrumentation/crewai/crewai.py
tmam/instrumentation/dynamiq/__init__.py
tmam/instrumentation/dynamiq/dynamiq.py
tmam/instrumentation/elevenlabs/__init__.py
tmam/instrumentation/elevenlabs/async_elevenlabs.py
tmam/instrumentation/elevenlabs/elevenlabs.py
tmam/instrumentation/embedchain/__init__.py
tmam/instrumentation/embedchain/embedchain.py
tmam-1.2.dist-info/METADATA
tmam-1.2.dist-info/WHEEL
tmam-1.2.dist-info/licenses/LICENSE
tmam-1.2.dist-info/RECORD
